ambition_ae/__init__.py
ambition_ae/action_items.py
ambition_ae/admin_site.py
ambition_ae/apps.py
ambition_ae/baker_recipes.py
ambition_ae/choices.py
ambition_ae/constants.py
ambition_ae/list_data.py
ambition_ae/navbars.py
ambition_ae/offline_models.py
ambition_ae/urls.py
ambition_ae/wsgi.py
ambition_ae/admin/__init__.py
ambition_ae/admin/ae_followup_admin.py
ambition_ae/admin/ae_initial_admin.py
ambition_ae/admin/ae_susar_admin.py
ambition_ae/admin/ae_tmg_admin.py
ambition_ae/admin/death_report_admin.py
ambition_ae/admin/death_report_tmg_admin.py
ambition_ae/admin/death_report_tmg_second_admin.py
ambition_ae/admin/list_model_admin.py
ambition_ae/admin/recurrence_symptom_admin.py
ambition_ae/form_validators/__init__.py
ambition_ae/form_validators/ae_initial.py
ambition_ae/form_validators/death_report.py
ambition_ae/form_validators/death_report_tmg.py
ambition_ae/form_validators/recurrence_symptom.py
ambition_ae/forms/__init__.py
ambition_ae/forms/recurrence_symptom_form.py
ambition_ae/migrations/0001_initial.py
ambition_ae/migrations/0002_auto_20180409_1213.py
ambition_ae/migrations/0003_auto_20180707_2155.py
ambition_ae/migrations/0004_auto_20180809_0504.py
ambition_ae/migrations/0005_auto_20180813_0311.py
ambition_ae/migrations/0006_auto_20180814_0313.py
ambition_ae/migrations/0007_auto_20180823_2235.py
ambition_ae/migrations/0008_auto_20180901_1512.py
ambition_ae/migrations/0009_auto_20180901_1512.py
ambition_ae/migrations/0010_auto_20180906_0750.py
ambition_ae/migrations/0011_auto_20181007_0053.py
ambition_ae/migrations/0012_auto_20181009_0545.py
ambition_ae/migrations/0013_auto_20181007_0100.py
ambition_ae/migrations/0014_auto_20181009_0637.py
ambition_ae/migrations/0015_auto_20181009_1633.py
ambition_ae/migrations/0016_auto_20181031_0628.py
ambition_ae/migrations/0017_auto_20181108_0353.py
ambition_ae/migrations/0018_auto_20181108_0632.py
ambition_ae/migrations/0019_auto_20181113_0715.py
ambition_ae/migrations/0020_auto_20181128_1649.py
ambition_edc-0.3.72.dist-info/AUTHORS
ambition_edc-0.3.72.dist-info/LICENSE
ambition_edc-0.3.72.dist-info/METADATA
ambition_edc-0.3.72.dist-info/WHEEL
ambition_edc-0.3.72.dist-info/top_level.txt
ambition_edc-0.3.72.dist-info/RECORD
