Metadata-Version: 2.1
Name: ambition-edc
Version: 0.3.72
Summary: Ambition Trial EDC (https://doi.org/10.1186/ISRCTN72509687)
Home-page: https://github.com/ambition-trial/ambition-edc
Author: Erik van Widenfelt
Author-email: ew2789@gmail.com
License: GPL license, see LICENSE
Keywords: django ambition EDC
Platform: UNKNOWN
Classifier: Environment :: Web Environment
Classifier: Framework :: Django
Classifier: Intended Audience :: Developers
Classifier: Intended Audience :: Science/Research
Classifier: License :: OSI Approved :: GNU General Public License v3 (GPLv3)
Classifier: Operating System :: OS Independent
Classifier: Programming Language :: Python :: 3.7
Classifier: Topic :: Internet :: WWW/HTTP
Classifier: Topic :: Internet :: WWW/HTTP :: Dynamic Content
Requires-Python: >=3.7
Requires-Dist: boto3
Requires-Dist: django[argon] (==2.2.10)
Requires-Dist: django-environ
Requires-Dist: django-redis
Requires-Dist: django-storages
Requires-Dist: celery
Requires-Dist: django-celery-beat
Requires-Dist: django-celery-results
Requires-Dist: gunicorn
Requires-Dist: python-memcached
Requires-Dist: pyrabbit
Requires-Dist: sentry-sdk
Requires-Dist: edc (==0.1.7)
